{
  "12-05-2023": [
    {
      "date": "11-27-2023",
      "image": "https://robohash.org/quasiveritatisdoloremque.png?size=50x50&set=set1",
      "title": "Polarised object-oriented middleware"
    },
    {
      "date": "7-17-2023",
      "image": "https://robohash.org/repellataliquamqui.png?size=50x50&set=set1",
      "title": "Optional mission-critical service-desk"
    },
    {
      "date": "9-22-2023",
      "image": "https://robohash.org/quodquaeratdistinctio.png?size=50x50&set=set1",
      "title": "Mandatory client-server matrix"
    },
    {
      "date": "9-29-2023",
      "image": "https://robohash.org/enimsintitaque.png?size=50x50&set=set1",
      "title": "Secured local system engine"
    },
    {
      "date": "6-4-2023",
      "image": "https://robohash.org/hicomnisitaque.png?size=50x50&set=set1",
      "title": "Persistent global process improvement"
    },
    {
      "date": "11-29-2023",
      "image": "https://robohash.org/doloreestaliquam.png?size=50x50&set=set1",
      "title": "Centralized explicit standardization"
    },
    {
      "date": "5-21-2023",
      "image": "https://robohash.org/quisautnobis.png?size=50x50&set=set1",
      "title": "Front-line non-volatile capability"
    },
    {
      "date": "9-14-2023",
      "image": "https://robohash.org/solutaquisquamhic.png?size=50x50&set=set1",
      "title": "Proactive systemic encryption"
    },
    {
      "date": "11-27-2023",
      "image": "https://robohash.org/adipiscirerumvelit.png?size=50x50&set=set1",
      "title": "Future-proofed 3rd generation artificial intelligence"
    },
    {
      "date": "11-27-2023",
      "image": "https://robohash.org/doloremdoloresharum.png?size=50x50&set=set1",
      "title": "Synergized multi-state projection"
    }
  ],
  "15-05-2023": [
    {
      "date": "11-27-2023",
      "image": "https://robohash.org/quasiveritatisdoloremque.png?size=50x50&set=set1",
      "title": "Polarised object-oriented middleware"
    },
    {
      "date": "7-17-2023",
      "image": "https://robohash.org/repellataliquamqui.png?size=50x50&set=set1",
      "title": "Optional mission-critical service-desk"
    },
    {
      "date": "9-22-2023",
      "image": "https://robohash.org/quodquaeratdistinctio.png?size=50x50&set=set1",
      "title": "Mandatory client-server matrix"
    },
    {
      "date": "9-29-2023",
      "image": "https://robohash.org/enimsintitaque.png?size=50x50&set=set1",
      "title": "Secured local system engine"
    },
    {
      "date": "6-4-2023",
      "image": "https://robohash.org/hicomnisitaque.png?size=50x50&set=set1",
      "title": "Persistent global process improvement"
    },
    {
      "date": "11-29-2023",
      "image": "https://robohash.org/doloreestaliquam.png?size=50x50&set=set1",
      "title": "Centralized explicit standardization"
    },
    {
      "date": "5-21-2023",
      "image": "https://robohash.org/quisautnobis.png?size=50x50&set=set1",
      "title": "Front-line non-volatile capability"
    },
    {
      "date": "9-14-2023",
      "image": "https://robohash.org/solutaquisquamhic.png?size=50x50&set=set1",
      "title": "Proactive systemic encryption"
    },
    {
      "date": "11-27-2023",
      "image": "https://robohash.org/adipiscirerumvelit.png?size=50x50&set=set1",
      "title": "Future-proofed 3rd generation artificial intelligence"
    },
    {
      "date": "11-27-2023",
      "image": "https://robohash.org/doloremdoloresharum.png?size=50x50&set=set1",
      "title": "Synergized multi-state projection"
    }
  ]
}
